bridgebots_tools/__init__.py
bridgebots_tools/compare_contracts_csv_report.py
bridgebots_tools/csv_report.py
bridgebots_tools/csv_utilities.py
bridgebots_tools/data_extractors.py
bridgebots_tools/practice.csv
bridgebots_tools/practice.lin
bridgebots_tools/practice_deals.py
bridgebots_tools/tools_logging.py
bridgebots_tools-0.0.5.dist-info/WHEEL
bridgebots_tools-0.0.5.dist-info/METADATA
bridgebots_tools-0.0.5.dist-info/RECORD
