Metadata-Version: 2.1
Name: bridgebots-tools
Version: 0.0.5
Summary: Tools which utilize the Bridgebots package to process data
License: MIT
Author: Forrest Rice
Author-email: forrest.d.rice@gmail.com
Requires-Python: >=3.7,<4.0
Classifier: License :: OSI Approved :: MIT License
Classifier: Programming Language :: Python :: 3
Classifier: Programming Language :: Python :: 3.7
Classifier: Programming Language :: Python :: 3.8
Classifier: Programming Language :: Python :: 3.9
Classifier: Programming Language :: Python :: 3.10
Classifier: Programming Language :: Python :: 3.11
Requires-Dist: bridgebots (==0.0.11a1)
Requires-Dist: click (>=8.0.3,<9.0.0)
